frappeviz/__init__.py
frappeviz/__main__.py
frappeviz/frappeviz.py
frappeviz-0.0.2.dist-info/LICENSE
frappeviz-0.0.2.dist-info/METADATA
frappeviz-0.0.2.dist-info/WHEEL
frappeviz-0.0.2.dist-info/entry_points.txt
frappeviz-0.0.2.dist-info/top_level.txt
frappeviz-0.0.2.dist-info/RECORD
