Metadata-Version: 2.1
Name: frappeviz
Version: 0.0.2
Summary: Python app for visualizing class diagrams for a Frappe Framework App using PlantUML
Home-page: https://github.com/yemikudaisi/frappeviz
Author: Yemi Kudaisi
Author-email: contact@yemikudaisi.online
License: UNKNOWN
Platform: UNKNOWN
Classifier: Programming Language :: Python :: 3
Classifier: License :: OSI Approved :: MIT License
Classifier: Operating System :: OS Independent
Requires-Python: >=3.6
Requires-Dist: plantuml (==0.3.0)
